{"cameraMode":{"drawMode":0,"name":"Shaded","section":"Shading Mode"},"sceneLighting":false,"audioPlay":false,"sceneViewState":{"m_AlwaysRefresh":false,"showFog":true,"showSkybox":true,"showFlares":true,"showImageEffects":true,"showParticleSystems":true,"showVisualEffectGraphs":true,"m_FxEnabled":true},"in2DMode":false,"pivot":{"x":-9.172252655029297,"y":0.569066047668457,"z":3.7557945251464845},"rotation":{"x":-0.16036388278007508,"y":-0.1057979017496109,"z":0.017291836440563203,"w":-0.981225848197937},"size":9.472896575927735,"orthographic":false}